Metadata-Version: 2.1
Name: djangoplicity-html2text
Version: 3.200.3
Summary: Turn HTML into equivalent Markdown-structured text.
Home-page: https://github.com/djangoplicity/djangoplicity-html2text
Author: Aaron Swartz
Author-email: me@aaronsw.com
License: GNU GPL 3
Download-URL: https://github.com/djangoplicity/djangoplicity-html2text/archive/refs/tags/3.200.3.tar.gz
Platform: UNKNOWN
Classifier: Development Status :: 5 - Production/Stable
Classifier: Intended Audience :: Developers
Classifier: License :: OSI Approved :: GNU General Public License (GPL)
Classifier: Programming Language :: Python
Classifier: Programming Language :: Python :: 2
Classifier: Programming Language :: Python :: 2.3
Classifier: Programming Language :: Python :: 2.4
Classifier: Programming Language :: Python :: 2.5
Classifier: Programming Language :: Python :: 2.6
Classifier: Programming Language :: Python :: 2.7
Classifier: Programming Language :: Python :: 3
Classifier: Programming Language :: Python :: 3.0
Classifier: Programming Language :: Python :: 3.1
Classifier: Programming Language :: Python :: 3.2
License-File: COPYING
